Metadata-Version: 2.1
Name: XStatic-pathseg
Version: 1.2.1.1
Summary: pathseg 1.2.1 (XStatic packaging standard)
Home-page: https://github.com/progers/pathseg
Maintainer: Roger Haase
Maintainer-email: haaserd@gmail.com
License: (same as pathseg)
Keywords: pathseg xstatic
Platform: any
License-File: LICENSE
